setup.py
wkb_raster.py
WKB_Raster.egg-info/PKG-INFO
WKB_Raster.egg-info/SOURCES.txt
WKB_Raster.egg-info/dependency_links.txt
WKB_Raster.egg-info/requires.txt
WKB_Raster.egg-info/top_level.txt