Metadata-Version: 1.0
Name: WKB-Raster
Version: 0.2
Summary: Read WKB rasters to Numpy arrays.
Home-page: https://github.com/nathancahill/wkb-raster
Author: Nathan Cahill
Author-email: nathan@nathancahill.com
License: MIT
Platform: UNKNOWN
